{
    "vscode-pets.panel.title": "Deltarune Characters",
    "vscode-pets.start.title": "Start Deltarune character session",
    "vscode-pets.throw-with-mouse.title": "Throw ball with mouse",
    "vscode-pets.throw-ball.title": "Throw ball",
    "vscode-pets.export-pet-list.title": "Export character list",
    "vscode-pets.import-pet-list.title": "Import character list",
    "vscode-pets.spawn-pet.title": "Spawn character",
    "vscode-pets.delete-pet.title": "Delete character",
    "vscode-pets.remove-all-pets.title": "Remove all characters",
    "vscode-pets.roll-call.title": "Roll call",
    "vscode-pets.petColor.description": "Character world",
    "vscode-pets.petType.description": "Deltarune character",
    "vscode-pets.petSize.description": "Character size",
    "vscode-pets.position.description": "Position of the character panel",
    "vscode-pets.theme.description": "Theme",
    "vscode-pets.throwBallWithMouse.description": "Throw ball with mouse",
    "vscode-pets.disableEffects.description": "Disable effects",
    "vscode-pets.petColor.darkworld": "Dark World",
    "vscode-pets.petType.kris": "Kris",
    "vscode-pets.petType.lancer": "Lancer",
    "vscode-pets.petType.ralsei": "Ralsei",
    "vscode-pets.petType.noelle": "Noelle",
    "vscode-pets.petType.susie": "Susie",
    "vscode-pets.petType.spamton": "Spamton",
    "vscode-pets.petType.jevil": "Jevil",
    "vscode-pets.petType.tenna": "Tenna",
    "vscode-pets.petSize.nano": "Nano",
    "vscode-pets.petSize.small": "Small",
    "vscode-pets.petSize.medium": "Medium",
    "vscode-pets.petSize.large": "Large",
    "vscode-pets.position.panel": "Panel",
    "vscode-pets.position.explorer": "Explorer",
    "vscode-pets.theme.none": "None",
    "vscode-pets.theme.forest": "Forest",
    "vscode-pets.theme.castle": "Castle",
    "vscode-pets.theme.beach": "Beach",
    "vscode-pets.theme.winter": "Winter",
    "vscode-pets.theme.autumn": "Autumn"
}
